CHANGELOG.rst
LICENSE.txt
MANIFEST.in
README.rst
Readme.txt
requirements.txt
setup.cfg
setup.py
./pyalexaskill/AlexaAudioBaseHandler.py
./pyalexaskill/AlexaBaseHandler.py
./pyalexaskill/AlexaUtils.py
./pyalexaskill/__init__.py
./pyalexaskill/tests/AlexaDeploymentHandler.py
./pyalexaskill/tests/__init__.py
./pyalexaskill/tests/main.py
bin/create_alexa_audio_handler.py
bin/create_alexa_handler.py
bin/create_alexa_test_skills.py
bin/create_aws_lambda.py
bin/create_aws_main.py
bin/create_test_deployment.py
pyalexa_skill.egg-info/PKG-INFO
pyalexa_skill.egg-info/SOURCES.txt
pyalexa_skill.egg-info/dependency_links.txt
pyalexa_skill.egg-info/not-zip-safe
pyalexa_skill.egg-info/requires.txt
pyalexa_skill.egg-info/top_level.txt