Metadata-Version: 1.1
Name: pyalexa-skill
Version: 0.2.9
Summary: Python module with a base class to support an Alexa skill set, and scripts to build an AWS python distibution
Home-page: https://github.com/youngsoul/PyAlexa
Author: Patrick Ryan
Author-email: pat_ryan_99@yahoo.com
License: Public Domain
Keywords: alexa,skill
Platform: UNKNOWN
Classifier: Development Status :: 4 - Beta
Classifier: Intended Audience :: Developers
Classifier: Natural Language :: English
Classifier: License :: Public Domain
Classifier: Operating System :: OS Independent
Classifier: Programming Language :: Python
Classifier: Programming Language :: Python :: 2
Classifier: Programming Language :: Python :: 2.7
Classifier: Programming Language :: Python :: 3
Classifier: Programming Language :: Python :: 3.4
Classifier: Programming Language :: Python :: 3.5
Classifier: Programming Language :: Python :: 3.6
Classifier: Topic :: Software Development :: Libraries :: Python Modules
